pyoptinterface/__init__.py
pyoptinterface/gurobi.py
pyoptinterface/nl.py
pyoptinterface/highs.py
pyoptinterface/mosek.py
pyoptinterface/ipopt.py
pyoptinterface/copt.py
pyoptinterface/_src/ipopt_model_ext.pyi
pyoptinterface/_src/constraint_bridge.py
pyoptinterface/_src/matrix.py
pyoptinterface/_src/jit_c.py
pyoptinterface/_src/core_ext.pyi
pyoptinterface/_src/nlexpr_ext.pyi
pyoptinterface/_src/highs_model_ext.pyi
pyoptinterface/_src/tupledict.py
pyoptinterface/_src/attributes.py
pyoptinterface/_src/__init__.py
pyoptinterface/_src/jit_llvm.py
pyoptinterface/_src/gurobi_model_ext.cpython-311-darwin.so
pyoptinterface/_src/cppad_interface_ext.cpython-311-darwin.so
pyoptinterface/_src/copt_model_ext.cpython-311-darwin.so
pyoptinterface/_src/aml.py
pyoptinterface/_src/nleval_ext.pyi
pyoptinterface/_src/tcc_interface_ext.pyi
pyoptinterface/_src/core_ext.cpython-311-darwin.so
pyoptinterface/_src/solver_common.py
pyoptinterface/_src/highs_model_ext.cpython-311-darwin.so
pyoptinterface/_src/gurobi.py
pyoptinterface/_src/nleval_ext.cpython-311-darwin.so
pyoptinterface/_src/highs.py
pyoptinterface/_src/gurobi_model_ext.pyi
pyoptinterface/_src/mosek.py
pyoptinterface/_src/ipopt.py
pyoptinterface/_src/mosek_model_ext.pyi
pyoptinterface/_src/cpp_graph_iter.py
pyoptinterface/_src/ipopt_model_ext.cpython-311-darwin.so
pyoptinterface/_src/codegen_llvm.py
pyoptinterface/_src/mosek_model_ext.cpython-311-darwin.so
pyoptinterface/_src/tcc_interface_ext.cpython-311-darwin.so
pyoptinterface/_src/copt_model_ext.pyi
pyoptinterface/_src/nlexpr_ext.cpython-311-darwin.so
pyoptinterface/_src/cppad_interface_ext.pyi
pyoptinterface/_src/monkeypatch.py
pyoptinterface/_src/copt.py
pyoptinterface/_src/comparison_constraint.py
pyoptinterface/_src/dylib.py
pyoptinterface/_src/codegen_c.py
pyoptinterface/_src/nlfunc.py
pyoptinterface-0.5.1.dist-info/RECORD
pyoptinterface-0.5.1.dist-info/WHEEL
pyoptinterface-0.5.1.dist-info/METADATA
pyoptinterface-0.5.1.dist-info/licenses/LICENSE.md
