Metadata-Version: 2.2
Name: pyoptinterface
Version: 0.5.1
Summary: Python interface to multiple optimization solvers
Author-Email: Yue Yang <metab0t@outlook.com>
Classifier: Development Status :: 5 - Production/Stable
Classifier: Intended Audience :: Science/Research
Classifier: Topic :: Scientific/Engineering
Classifier: License :: OSI Approved :: Mozilla Public License 2.0 (MPL 2.0)
Project-URL: Homepage, https://github.com/metab0t/pyoptinterface
Requires-Python: >=3.9
Provides-Extra: matrix
Requires-Dist: numpy; extra == "matrix"
Requires-Dist: scipy; extra == "matrix"
Provides-Extra: highs
Requires-Dist: highsbox; extra == "highs"
Provides-Extra: nlp
Requires-Dist: llvmlite; extra == "nlp"
Requires-Dist: tccbox; extra == "nlp"
Provides-Extra: test
Requires-Dist: pytest; extra == "test"
Requires-Dist: numpy; extra == "test"
Requires-Dist: scipy>=1.11.0; extra == "test"
Requires-Dist: highsbox; extra == "test"
Requires-Dist: llvmlite; extra == "test"
Requires-Dist: tccbox; extra == "test"
